getpic/__init__.py
getpic/api.py
getpic/crawl_baidu.py
getpic/crawl_google.py
getpic/crawl_image.py
getpic/crawl_so.py
getpic/crawl_sogou.py
getpic/libs/__init__.py
getpic/libs/download_progress.py
getpic/libs/json_conf.py
getpic-1.0.4.dist-info/LICENSE
getpic-1.0.4.dist-info/METADATA
getpic-1.0.4.dist-info/WHEEL
getpic-1.0.4.dist-info/entry_points.txt
getpic-1.0.4.dist-info/top_level.txt
getpic-1.0.4.dist-info/RECORD
