Metadata-Version: 2.1
Name: getpic
Version: 1.0.4
Summary: Crawl image from Google or Baidu search engine
Home-page: https://github.com/jianboy/getpic
Author: lyq
Author-email: liuyuqi.gov@msn.cn
License: UNKNOWN
Platform: UNKNOWN
License-File: LICENSE
Requires-Dist: requests (==2.28.0)
Requires-Dist: selenium (==4.2.0)
Provides-Extra: dev
Requires-Dist: pytest ; extra == 'dev'
